{
	"configurations" : 
	[
		{
			"directories" : 
			[
				{
					"build" : ".",
					"hasInstallRule" : true,
					"jsonFile" : "directory-.-87b22181a027eb6d0bf6.json",
					"minimumCMakeVersion" : 
					{
						"string" : "3.10.2"
					},
					"projectIndex" : 0,
					"source" : ".",
					"targetIndexes" : 
					[
						0,
						1
					]
				}
			],
			"name" : "",
			"projects" : 
			[
				{
					"directoryIndexes" : 
					[
						0
					],
					"name" : "panda_moveit",
					"targetIndexes" : 
					[
						0,
						1
					]
				}
			],
			"targets" : 
			[
				{
					"directoryIndex" : 0,
					"id" : "panda_moveit_uninstall::@6890427a1f51a3e7e1df",
					"jsonFile" : "target-panda_moveit_uninstall-49b56dfd472eba09a5dd.json",
					"name" : "panda_moveit_uninstall",
					"projectIndex" : 0
				},
				{
					"directoryIndex" : 0,
					"id" : "uninstall::@6890427a1f51a3e7e1df",
					"jsonFile" : "target-uninstall-9b86e85337339b8ab5c9.json",
					"name" : "uninstall",
					"projectIndex" : 0
				}
			]
		}
	],
	"kind" : "codemodel",
	"paths" : 
	{
		"build" : "/home/minis/ws_moveit2/build/panda_moveit",
		"source" : "/home/minis/ws_moveit2/src/panda_moveit"
	},
	"version" : 
	{
		"major" : 2,
		"minor" : 3
	}
}
